oci_mlflow/__init__.py
oci_mlflow/auth_plugin.py
oci_mlflow/deployment.py
oci_mlflow/oci_object_storage.py
oci_mlflow/project.py
oci_mlflow/telemetry_logging.py
oci_mlflow/utils.py
oci_mlflow/templates/__init__.py
oci_mlflow/templates/project_description.jinja2
oci_mlflow/templates/runtime.yaml.jinja2
oci_mlflow/templates/score.py.jinja2
oci_mlflow-1.0.3.dist-info/entry_points.txt
oci_mlflow-1.0.3.dist-info/licenses/LICENSE.txt
oci_mlflow-1.0.3.dist-info/WHEEL
oci_mlflow-1.0.3.dist-info/METADATA
oci_mlflow-1.0.3.dist-info/RECORD
