Metadata-Version: 2.4
Name: oci-mlflow
Version: 1.0.3
Summary: OCI MLflow plugin to use OCI resources within MLflow
Keywords: Oracle Cloud Infrastructure,OCI,Object Storage,MLflow
Author: Oracle Cloud Infrastructure Data Science
Requires-Python: >=3.10
Classifier: Development Status :: 5 - Production/Stable
Classifier: Intended Audience :: Developers
Classifier: License :: OSI Approved :: Universal Permissive License (UPL)
Classifier: Operating System :: OS Independent
Classifier: Programming Language :: Python :: 3.10
Classifier: Programming Language :: Python :: 3.11
Classifier: Programming Language :: Python :: 3.12
License-File: LICENSE.txt
Requires-Dist: mlflow>=3.8.1
Requires-Dist: oracle-ads>=2.14.4
Project-URL: Documentation, https://oci-mlflow.readthedocs.io/en/latest/index.html
Project-URL: Github, https://github.com/oracle/oci-mlflow
